sentimetrics.cp311-win_amd64.pyd
sentimetrics-1.0.0.dist-info/METADATA
sentimetrics-1.0.0.dist-info/WHEEL
sentimetrics-1.0.0.dist-info/top_level.txt
sentimetrics-1.0.0.dist-info/RECORD
