Metadata-Version: 2.1
Name: sentimetrics
Version: 1.0.0
Summary: Analyze sentiment of text
Home-page: https://github.com/Emeson-Borges/sentimetrics
Author: Emeson Borges
Author-email: borges2016.leh@gmail.com
